s3_client_server_side/__init__.py
s3_client_server_side/s3_client.py
s3_client_server_side-1.0.1.dist-info/METADATA
s3_client_server_side-1.0.1.dist-info/WHEEL
s3_client_server_side-1.0.1.dist-info/top_level.txt
s3_client_server_side-1.0.1.dist-info/zip-safe
s3_client_server_side-1.0.1.dist-info/RECORD
